AUTHORS.rst
CONTRIBUTING.rst
HISTORY.rst
LICENSE
MANIFEST.in
README.rst
menu_generator.py
setup.cfg
setup.py
docs/Makefile
docs/authors.rst
docs/conf.py
docs/contributing.rst
docs/history.rst
docs/index.rst
docs/installation.rst
docs/make.bat
docs/readme.rst
docs/usage.rst
menugen.egg-info/PKG-INFO
menugen.egg-info/SOURCES.txt
menugen.egg-info/dependency_links.txt
menugen.egg-info/not-zip-safe
menugen.egg-info/top_level.txt
tests/__init__.py
tests/test_menugen.py