Metadata-Version: 1.1
Name: menugen
Version: 0.1.0
Summary: Generates menus for terminals
Home-page: https://github.com/iansmcf/menugen
Author: Ian McFarlane
Author-email: iansmcfarlane@gmail.com
License: BSD
Keywords: menugen
Platform: UNKNOWN
Classifier: Development Status :: 2 - Pre-Alpha
Classifier: Intended Audience :: Developers
Classifier: License :: OSI Approved :: BSD License
Classifier: Natural Language :: English
Classifier: Programming Language :: Python :: 2.7
